root_aligned/score.py
root_aligned/score_p2s2r.py
root_aligned/preprocessing/generate_PtoR_data.py
root_aligned/preprocessing/generate_PtoStoR_data.py
root_aligned/preprocessing/generate_RtoP_data.py
root_aligned/preprocessing/generate_masked_pretrain_data.py
root_aligned/preprocessing/generate_pretrain_data.py
root_aligned/preprocessing/get_R-SMILES.py
root_aligned/preprocessing/prepare_StoR.py
syntheseus_root_aligned-0.2.0.dist-info/licenses/LICENSE
syntheseus_root_aligned-0.2.0.dist-info/METADATA
syntheseus_root_aligned-0.2.0.dist-info/WHEEL
syntheseus_root_aligned-0.2.0.dist-info/top_level.txt
syntheseus_root_aligned-0.2.0.dist-info/RECORD
